Metadata-Version: 2.1
Name: libpyfdtcam
Version: 1.0.4
Summary: A lib to control FDT IP cameras.
Home-page: https://github.com/fastcrash/libpyfdtcam
Author: losse83
Author-email: losse83@posteo.de
License: UNKNOWN
Platform: UNKNOWN
Classifier: Programming Language :: Python :: 3
Classifier: License :: OSI Approved :: MIT License
Classifier: Operating System :: OS Independent
